easymcp/__init__.py
easymcp/py.typed
easymcp/client/ClientManager.py
easymcp/client/SessionMaker.py
easymcp/client/__init__.py
easymcp/client/iobuffers.py
easymcp/client/requestmap.py
easymcp/client/utils.py
easymcp/client/sessions/GenericSession.py
easymcp/client/sessions/__init__.py
easymcp/client/sessions/fastmcp/__init__.py
easymcp/client/sessions/fastmcp/main.py
easymcp/client/sessions/fastmcp/parameters.py
easymcp/client/sessions/mcp/__init__.py
easymcp/client/sessions/mcp/session.py
easymcp/client/transports/docker.py
easymcp/client/transports/generic.py
easymcp/client/transports/sse.py
easymcp/client/transports/stdio.py
easymcp-0.4.0.dist-info/METADATA
easymcp-0.4.0.dist-info/WHEEL
easymcp-0.4.0.dist-info/entry_points.txt
easymcp-0.4.0.dist-info/licenses/LICENSE
easymcp-0.4.0.dist-info/RECORD
