Metadata-Version: 2.4
Name: easymcp
Version: 0.4.0
Summary: Add your description here
Author-email: TerminalMan <84923604+SecretiveShell@users.noreply.github.com>
License-File: LICENSE
Requires-Python: >=3.13
Requires-Dist: aiodocker>=0.24.0
Requires-Dist: httpx>=0.28.1
Requires-Dist: loguru>=0.7.3
Requires-Dist: mcp>=1.5.0
Requires-Dist: pydantic>=2.10.6
